DP4plus_solv/DP4plus_solv.py
DP4plus_solv/UI.ui
DP4plus_solv/UI2.ui
DP4plus_solv/__init__.py
DP4plus_solv/Example_DP4plus_solvent/01_menthol_01_OptB_NMR_benzene.log
DP4plus_solv/Example_DP4plus_solvent/01_menthol_02_OptB_NMR_benzene.log
DP4plus_solv/Example_DP4plus_solvent/01_menthol_03_OptB_NMR_benzene.log
DP4plus_solv/Example_DP4plus_solvent/01_menthol_04_OptB_NMR_benzene.log
DP4plus_solv/Example_DP4plus_solvent/01_menthol_05_OptB_NMR_benzene.log
DP4plus_solv/Example_DP4plus_solvent/01_menthol_06_OptB_NMR_benzene.log
DP4plus_solv/Example_DP4plus_solvent/01_menthol_07_OptB_NMR_benzene.log
DP4plus_solv/Example_DP4plus_solvent/01_menthol_08_OptB_NMR_benzene.log
DP4plus_solv/Example_DP4plus_solvent/01_menthol_09_OptB_NMR_benzene.log
DP4plus_solv/Example_DP4plus_solvent/01_menthol_10_OptB_NMR_benzene.log
DP4plus_solv/Example_DP4plus_solvent/02_menthol_01_OptB_NMR_benzene.log
DP4plus_solv/Example_DP4plus_solvent/02_menthol_02_OptB_NMR_benzene.log
DP4plus_solv/Example_DP4plus_solvent/02_menthol_03_OptB_NMR_benzene.log
DP4plus_solv/Example_DP4plus_solvent/02_menthol_04_OptB_NMR_benzene.log
DP4plus_solv/Example_DP4plus_solvent/02_menthol_05_OptB_NMR_benzene.log
DP4plus_solv/Example_DP4plus_solvent/02_menthol_06_OptB_NMR_benzene.log
DP4plus_solv/Example_DP4plus_solvent/02_menthol_07_OptB_NMR_benzene.log
DP4plus_solv/Example_DP4plus_solvent/02_menthol_08_OptB_NMR_benzene.log
DP4plus_solv/Example_DP4plus_solvent/02_menthol_09_OptB_NMR_benzene.log
DP4plus_solv/Example_DP4plus_solvent/02_menthol_10_OptB_NMR_benzene.log
DP4plus_solv/Example_DP4plus_solvent/02_menthol_11_OptB_NMR_benzene.log
DP4plus_solv/Example_DP4plus_solvent/02_menthol_12_OptB_NMR_benzene.log
DP4plus_solv/Example_DP4plus_solvent/02_menthol_13_OptB_NMR_benzene.log
DP4plus_solv/Example_DP4plus_solvent/02_menthol_14_OptB_NMR_benzene.log
DP4plus_solv/Example_DP4plus_solvent/02_menthol_15_OptB_NMR_benzene.log
DP4plus_solv/Example_DP4plus_solvent/02_menthol_16_OptB_NMR_benzene.log
DP4plus_solv-1.1.1.dist-info/LICENCE
DP4plus_solv-1.1.1.dist-info/METADATA
DP4plus_solv-1.1.1.dist-info/WHEEL
DP4plus_solv-1.1.1.dist-info/entry_points.txt
DP4plus_solv-1.1.1.dist-info/top_level.txt
DP4plus_solv-1.1.1.dist-info/RECORD
