Metadata-Version: 2.1
Name: DP4plus-solv
Version: 1.1.1
Summary: Solvent DP4+: Impact of solvent effects on DP4+ assignments
Home-page: https://github.com/Sarotti-Lab/DP4plus_solv
Author: Maria M. Zanardi & Ariel M. Sarotti
Author-email: zanardi@rosario-conicet.gov.ar
License: MIT
Keywords: NMR structural elucidation
Classifier: Programming Language :: Python :: 3
Classifier: License :: OSI Approved :: MIT License
Classifier: Operating System :: OS Independent
License-File: LICENCE
Requires-Dist: pandas
Requires-Dist: numpy
Requires-Dist: scipy
Requires-Dist: openpyxl
Requires-Dist: pathlib
Requires-Dist: pyqt5
Requires-Dist: scikit-learn
